src/__init__.py
dore/__init__.py
dore/__main__.py
dore/attribute/__init__.py
dore/attribute/attribute.py
dore/attribute/attribute_container.py
dore/attribute/attribute_container_factory.py
dore/attribute/attribute_factory.py
dore/attribute/attribute_value_generator.py
dore/attribute/config/__init__.py
dore/attribute/config/attribute_config.py
dore/attribute/config/attribute_container_config.py
dore/attribute/config/attribute_container_schema.py
dore/attribute/config/attribute_definition_schema.py
dore/attribute/config/attribute_properties_schema.py
dore/attribute/config/attribute_reference_schema.py
dore/attribute/config/attribute_schema.py
dore/attribute/config/attribute_value_schema.py
dore/attribute/value_generators/__init__.py
dore/attribute/value_generators/composite/__init__.py
dore/attribute/value_generators/composite/composite_value_generator.py
dore/attribute/value_generators/composite/config/__init__.py
dore/attribute/value_generators/composite/config/composite_value_generator_config.py
dore/attribute/value_generators/composite/config/composite_value_generator_schema.py
dore/attribute/value_generators/d_attribute_value_generator.py
dore/attribute/value_generators/dependency.py
dore/attribute/value_generators/faker/__init__.py
dore/attribute/value_generators/faker/config/__init__.py
dore/attribute/value_generators/faker/config/faker_value_generator_config.py
dore/attribute/value_generators/faker/config/faker_value_generator_schema.py
dore/attribute/value_generators/faker/faker_value_generator.py
dore/attribute/value_generators/faker/utils/__init__.py
dore/attribute/value_generators/faker/utils/param_transformer.py
dore/attribute/value_generators/i_attribute_value_generator.py
dore/attribute/value_generators/ref/__init__.py
dore/attribute/value_generators/ref/config/__init__.py
dore/attribute/value_generators/ref/config/ref_value_generator_config.py
dore/attribute/value_generators/ref/config/ref_value_generator_schema.py
dore-1.1.4.dist-info/entry_points.txt
dore-1.1.4.dist-info/LICENSE
dore-1.1.4.dist-info/WHEEL
dore-1.1.4.dist-info/METADATA
dore-1.1.4.dist-info/RECORD
