Metadata-Version: 2.1
Name: dore
Version: 1.1.4
Summary: Schema based fake data generator
Home-page: https://dore-datagen.github.io/
License: Apache-2.0
Author: Bhargav KN
Author-email: bhargavkn.1996@gmail.com
Requires-Python: >=3.7,<4.0
Classifier: License :: OSI Approved :: Apache Software License
Classifier: Programming Language :: Python :: 3
Classifier: Programming Language :: Python :: 3.7
Classifier: Programming Language :: Python :: 3.8
Classifier: Programming Language :: Python :: 3.9
Classifier: Programming Language :: Python :: 3.10
Classifier: Programming Language :: Python :: 3.11
Requires-Dist: Faker (>=13.4.0)
Requires-Dist: PyPika (>=0.48.9)
Requires-Dist: elasticsearch7 (>=7.17.2,<8)
Requires-Dist: elasticsearch8 (>=8.1.2,<9)
Requires-Dist: jsonschema (>=4.6.1)
Requires-Dist: mysqlclient (>=2.1.0)
Requires-Dist: psycopg (>=3.0.11)
Requires-Dist: pymongo (>=4.1.1)
Requires-Dist: pystache (>=0.6.0)
Requires-Dist: redis (>=4.3.3)
Requires-Dist: tqdm (>=4.64.1)
Project-URL: Repository, https://github.com/dore-datagen/dore-py
